hack4u_darabe/__init__.py
hack4u_darabe/courses.py
hack4u_darabe/utils.py
hack4u_darabe-0.1.1.dist-info/METADATA
hack4u_darabe-0.1.1.dist-info/WHEEL
hack4u_darabe-0.1.1.dist-info/top_level.txt
hack4u_darabe-0.1.1.dist-info/RECORD
