Metadata-Version: 2.1
Name: hack4u_darabe
Version: 0.1.1
Home-page: https://hack4u.io
Author: David Ramos
